strip_ast_comments.py
strip_python3.py
strip_qtoml_decoder.py
strip_python3-1.1.1134.dist-info/licenses/LICENSE
strip_python3-1.1.1134.dist-info/METADATA
strip_python3-1.1.1134.dist-info/WHEEL
strip_python3-1.1.1134.dist-info/entry_points.txt
strip_python3-1.1.1134.dist-info/top_level.txt
strip_python3-1.1.1134.dist-info/RECORD
