Metadata-Version: 2.2
Name: strip_python3
Version: 1.1.1134
Summary: easy way to remove python3 typehints and to transform sources to older python compatibility
Author-email: "Guido U. Draheim" <Guido.Draheim@gmx.de>
License-Expression: MIT
Project-URL: homepage, https://github.com/gdraheim/strip_python3
Project-URL: repository, https://github.com/gdraheim/strip_python3.git
Project-URL: issues, https://github.com/gdraheim/strip_python3/issues
Classifier: Operating System :: POSIX :: Linux
Classifier: Environment :: Console
Classifier: Programming Language :: Python :: 3
Classifier: Programming Language :: Python :: 3.9
Classifier: Topic :: Software Development :: Code Generators
Classifier: Typing :: Typed
License-File: LICENSE
Provides-Extra: dev
Requires-Dist: build; extra == "dev"
Dynamic: license-file
